redpanda/__init__.py
redpanda/dialects.py
redpanda/example.py
redpanda/orm.py
redpanda-0.6.0.dist-info/LICENSE
redpanda-0.6.0.dist-info/WHEEL
redpanda-0.6.0.dist-info/METADATA
redpanda-0.6.0.dist-info/RECORD
