Metadata-Version: 2.1
Name: redpanda
Version: 0.6.0
Summary: Pandas-ORM Integration.
Author-email: Alexander Mancevice <alexander.mancevice@hey.com>
Requires-Python: >= 3.8
Classifier: Development Status :: 5 - Production/Stable
Classifier: Environment :: Console
Classifier: Intended Audience :: Developers
Classifier: License :: OSI Approved :: MIT License
Classifier: Operating System :: OS Independent
Classifier: Programming Language :: Python :: 3
Classifier: Programming Language :: Python :: 3.8
Classifier: Programming Language :: Python :: 3.9
Classifier: Programming Language :: Python :: 3.10
Classifier: Programming Language :: Python :: 3.11
Classifier: Programming Language :: Python :: 3.12
Classifier: Topic :: Utilities
Requires-Dist: pandas
Requires-Dist: sqlalchemy
Project-URL: Home, https://github.com/amancevice/redpanda
